README.rst
setup.py
x10_any/__init__.py
x10_any/cm17a.py
x10_any.egg-info/PKG-INFO
x10_any.egg-info/SOURCES.txt
x10_any.egg-info/dependency_links.txt
x10_any.egg-info/requires.txt
x10_any.egg-info/top_level.txt